test_pypi_package/__init__.py
test_pypi_package/main.py
test_pypi_package-0.0.2.dist-info/LICENSE
test_pypi_package-0.0.2.dist-info/METADATA
test_pypi_package-0.0.2.dist-info/WHEEL
test_pypi_package-0.0.2.dist-info/top_level.txt
test_pypi_package-0.0.2.dist-info/RECORD
